LICENSE
README.md
setup.cfg
setup.py
hbmo/__init__.py
hbmo/metrics.py
hbmo/optimization.py
hbmo.egg-info/PKG-INFO
hbmo.egg-info/SOURCES.txt
hbmo.egg-info/dependency_links.txt
hbmo.egg-info/requires.txt
hbmo.egg-info/top_level.txt