Metadata-Version: 2.1
Name: hbmo
Version: 1.0.3
Summary: implementation of HBMO and MHBMO optimization algorithms
Home-page: https://github.com/alimahmoodi78/hbmo
Download-URL: https://github.com/alimahmoodi78/hbmo/archive/refs/tags/v1.0.tar.gz
Author: Ali Mahmoodi
Author-email: ali.mahmoodi7872@gmail.com
License: MIT
Keywords: Swarm-Based Optimization,Honey-Bee Mating Optimization
Platform: UNKNOWN
License-File: LICENSE
